README.rst
setup.cfg
setup.py
nakama/__init__.py
nakama/nk_client/__init__.py
nakama/nk_client/channel.py
nakama/nk_client/event.py
nakama/nk_client/friends.py
nakama/nk_client/groups.py
nakama/nk_client/leaderboard.py
nakama/nk_client/matches.py
nakama/nk_client/nakama_client.py
nakama/nk_client/notifications.py
nakama/nk_client/purchase.py
nakama/nk_client/rpc.py
nakama/nk_client/session.py
nakama/nk_client/storage.py
nakama/nk_client/tournaments.py
nakama/nk_client/users.py
nakama/nk_client/account/__init__.py
nakama/nk_client/account/account.py
nakama/nk_client/account/authenticate.py
nakama/nk_client/account/link.py
nakama/nk_client/account/unlink.py
nakama/nk_socket/__init__.py
nakama/nk_socket/channel.py
nakama/nk_socket/handlers.py
nakama/nk_socket/match.py
nakama/nk_socket/matchmaker.py
nakama/nk_socket/nakama_socket.py
nakama/nk_socket/status.py
nakama/nk_socket/ws_helpers.py
nakama_python.egg-info/PKG-INFO
nakama_python.egg-info/SOURCES.txt
nakama_python.egg-info/dependency_links.txt
nakama_python.egg-info/not-zip-safe
nakama_python.egg-info/requires.txt
nakama_python.egg-info/top_level.txt