Metadata-Version: 2.1
Name: nakama-python
Version: 1.0.3
Summary: Python client for Nakama server
Home-page: https://github.com/ojengwa/nakama-python
Author: Bernard Ojengwa
Author-email: bernardojengwa@gmail.com
License: MIT
Keywords: nakama
Platform: UNKNOWN
